{
    "data_flow2": {
        "gui": {
            "editor_gaphas": {
                "waypoints": {}
            }
        }
    }, 
    "data_flow3": {
        "gui": {
            "editor_gaphas": {
                "waypoints": {}
            }
        }
    }, 
    "gui": {
        "editor_gaphas": {
            "background_color": false, 
            "name": {
                "rel_pos": {
                    "__jsonqualname__": "__builtin__.tuple", 
                    "items": [
                        0.9864276294653109, 
                        1.039018166936561
                    ]
                }, 
                "size": {
                    "__jsonqualname__": "__builtin__.tuple", 
                    "items": [
                        30.128188144383575, 
                        8.201533204733874
                    ]
                }
            }, 
            "rel_pos": {
                "__jsonqualname__": "__builtin__.tuple", 
                "items": [
                    77.31996465349803, 
                    27.258074413077168
                ]
            }, 
            "size": {
                "__jsonqualname__": "__builtin__.tuple", 
                "items": [
                    38.445938949018455, 
                    23.659961987301443
                ]
            }
        }
    }, 
    "income": {
        "gui": {
            "editor_gaphas": {
                "rel_pos": {
                    "__jsonqualname__": "__builtin__.tuple", 
                    "items": [
                        0.47319923974602895, 
                        2.0503833011834685
                    ]
                }
            }
        }
    }, 
    "outcome-1": {
        "gui": {
            "editor_gaphas": {
                "rel_pos": {
                    "__jsonqualname__": "__builtin__.tuple", 
                    "items": [
                        29.888679287540334, 
                        0.47319923974602895
                    ]
                }
            }
        }
    }, 
    "outcome-2": {
        "gui": {
            "editor_gaphas": {
                "rel_pos": {
                    "__jsonqualname__": "__builtin__.tuple", 
                    "items": [
                        28.331397766471287, 
                        0.47319923974602895
                    ]
                }
            }
        }
    }, 
    "outcome0": {
        "gui": {
            "editor_gaphas": {
                "rel_pos": {
                    "__jsonqualname__": "__builtin__.tuple", 
                    "items": [
                        37.972739709272425, 
                        2.0503833011834685
                    ]
                }
            }
        }
    }, 
    "scoped_variable0": {
        "gui": {
            "editor_gaphas": {
                "rel_pos": {
                    "__jsonqualname__": "__builtin__.tuple", 
                    "items": [
                        3.924203931604363, 
                        23.186762747555413
                    ]
                }
            }
        }
    }, 
    "transition13": {
        "gui": {
            "editor_gaphas": {
                "waypoints": []
            }
        }
    }, 
    "transition19": {
        "gui": {
            "editor_gaphas": {
                "waypoints": [
                    {
                        "__jsonqualname__": "__builtin__.tuple", 
                        "items": [
                            21.636708920079837, 
                            8.292616777342566
                        ]
                    }
                ]
            }
        }
    }, 
    "transition20": {
        "gui": {
            "editor_gaphas": {
                "waypoints": []
            }
        }
    }, 
    "transition21": {
        "gui": {
            "editor_gaphas": {
                "waypoints": []
            }
        }
    }, 
    "transition22": {
        "gui": {
            "editor_gaphas": {
                "waypoints": []
            }
        }
    }, 
    "transition23": {
        "gui": {
            "editor_gaphas": {
                "waypoints": []
            }
        }
    }
}